{
    "song_id": 5115,
    "revision_id": 637036,
    "prev_revision_id": 488665,
    "image": "v3-0-0-EBIQEj8cEQKDrNVq",
    "name": "Against_All_Odds",
    "tracks": [
        {
            "instrumentId": 0,
            "instrument": "Acoustic Grand Piano",
            "views": 448,
            "name": "Phil Collins (piano)",
            "tuning": [
                64,
                59,
                55,
                50,
                45,
                40
            ],
            "hash": "other_PjQm2Zpm",
            "title": "Phil Collins (piano) - Acoustic Grand Piano",
            "isDrums": false,
            "isBassGuitar": false,
            "isGuitar": false,
            "partId": 0,
            "originalPartId": 0
        },
        {
            "instrumentId": 50,
            "instrument": "SynthStrings 1",
            "views": 1,
            "name": "",
            "tuning": [
                64,
                59,
                55,
                50,
                45,
                40
            ],
            "hash": "other_PsrNju0C",
            "title": "SynthStrings 1",
            "isDrums": false,
            "isBassGuitar": false,
            "isGuitar": false,
            "partId": 1,
            "originalPartId": 1
        },
        {
            "instrumentId": 1,
            "instrument": "Bright Acoustic Piano",
            "views": 148,
            "name": "Phil Collins (melody)",
            "tuning": [
                64,
                59,
                55,
                50,
                45,
                40
            ],
            "hash": "other_DSYtQqSS",
            "title": "Phil Collins (melody) - Bright Acoustic Piano",
            "isDrums": false,
            "isBassGuitar": false,
            "isGuitar": false,
            "partId": 2,
            "originalPartId": 2
        },
        {
            "instrumentId": 35,
            "instrument": "Fretless Bass",
            "views": 170,
            "name": "",
            "tuning": [
                42,
                37,
                32,
                27
            ],
            "hash": "bass_YQSH7nON",
            "title": "Fretless Bass",
            "isDrums": false,
            "isBassGuitar": true,
            "isGuitar": false,
            "partId": 3,
            "originalPartId": 3
        },
        {
            "instrumentId": 1024,
            "instrument": "Drums",
            "views": 52,
            "name": "",
            "hash": "drums_AetNcIgd",
            "title": "Drums",
            "isDrums": true,
            "isBassGuitar": false,
            "isGuitar": false,
            "partId": 4,
            "originalPartId": 4
        }
    ],
    "original_tracks": [
        {
            "instrumentId": 0,
            "instrument": "Acoustic Grand Piano",
            "views": 448,
            "name": "Phil Collins (piano)",
            "tuning": [
                64,
                59,
                55,
                50,
                45,
                40
            ],
            "hash": "other_PjQm2Zpm",
            "title": "Phil Collins (piano) - Acoustic Grand Piano",
            "isDrums": false,
            "isBassGuitar": false,
            "isGuitar": false,
            "partId": 0
        },
        {
            "instrumentId": 50,
            "instrument": "SynthStrings 1",
            "views": 1,
            "name": "",
            "tuning": [
                64,
                59,
                55,
                50,
                45,
                40
            ],
            "hash": "other_PsrNju0C",
            "title": "SynthStrings 1",
            "isDrums": false,
            "isBassGuitar": false,
            "isGuitar": false,
            "partId": 1
        },
        {
            "instrumentId": 1,
            "instrument": "Bright Acoustic Piano",
            "views": 148,
            "name": "Phil Collins (melody)",
            "tuning": [
                64,
                59,
                55,
                50,
                45,
                40
            ],
            "hash": "other_DSYtQqSS",
            "title": "Phil Collins (melody) - Bright Acoustic Piano",
            "isDrums": false,
            "isBassGuitar": false,
            "isGuitar": false,
            "partId": 2
        },
        {
            "instrumentId": 35,
            "instrument": "Fretless Bass",
            "views": 170,
            "name": "",
            "tuning": [
                42,
                37,
                32,
                27
            ],
            "hash": "bass_YQSH7nON",
            "title": "Fretless Bass",
            "isDrums": false,
            "isBassGuitar": true,
            "isGuitar": false,
            "partId": 3
        },
        {
            "instrumentId": 1024,
            "instrument": "Drums",
            "views": 52,
            "name": "",
            "hash": "drums_AetNcIgd",
            "title": "Drums",
            "isDrums": true,
            "isBassGuitar": false,
            "isGuitar": false,
            "partId": 4
        }
    ]
}