{
    "song_id": 11549,
    "revision_id": 222662,
    "prev_revision_id": null,
    "image": "Ky--G3PpvrWzhBjCiT1lS",
    "name": "As_The_Palaces_Burn",
    "tracks": [
        {
            "instrumentId": 30,
            "instrument": "Distortion Guitar",
            "views": 3770,
            "name": "Willie Adler",
            "tuning": [
                64,
                59,
                55,
                50,
                45,
                38
            ],
            "difficulty": 4,
            "hash": "guitar_hF7BIQ5m",
            "title": "Willie Adler - Distortion Guitar",
            "isDrums": false,
            "isBassGuitar": false,
            "isGuitar": true,
            "partId": 0,
            "originalPartId": 0
        },
        {
            "instrumentId": 30,
            "instrument": "Distortion Guitar",
            "views": 288,
            "name": "Mark Morton",
            "tuning": [
                64,
                59,
                55,
                50,
                45,
                38
            ],
            "difficulty": 4,
            "hash": "guitar_sfDg1i7E",
            "title": "Mark Morton - Distortion Guitar",
            "isDrums": false,
            "isBassGuitar": false,
            "isGuitar": true,
            "partId": 1,
            "originalPartId": 1
        },
        {
            "instrumentId": 30,
            "instrument": "Distortion Guitar",
            "views": 421,
            "name": "Solo guitar 1",
            "tuning": [
                64,
                59,
                55,
                50,
                45,
                40
            ],
            "difficulty": 4,
            "hash": "guitar_g4kmgK6v",
            "title": "Solo guitar 1 - Distortion Guitar",
            "isDrums": false,
            "isBassGuitar": false,
            "isGuitar": true,
            "partId": 2,
            "originalPartId": 2
        },
        {
            "instrumentId": 30,
            "instrument": "Distortion Guitar",
            "views": 98,
            "name": "Solo guitar 2",
            "tuning": [
                64,
                59,
                55,
                50,
                45,
                38
            ],
            "difficulty": 4,
            "hash": "guitar_i0Xkk4Wm",
            "title": "Solo guitar 2 - Distortion Guitar",
            "isDrums": false,
            "isBassGuitar": false,
            "isGuitar": true,
            "partId": 3,
            "originalPartId": 3
        },
        {
            "instrumentId": 34,
            "instrument": "Electric Bass (pick)",
            "views": 313,
            "name": "John Campbell",
            "tuning": [
                43,
                38,
                33,
                26
            ],
            "hash": "bass_QVLYDfhW",
            "title": "John Campbell - Electric Bass (pick)",
            "isDrums": false,
            "isBassGuitar": true,
            "isGuitar": false,
            "partId": 4,
            "originalPartId": 4
        },
        {
            "instrumentId": 1024,
            "instrument": "Drums",
            "views": 17,
            "name": "Chris Adler",
            "hash": "drums_hES3js5s",
            "title": "Chris Adler - Drums",
            "isDrums": true,
            "isBassGuitar": false,
            "isGuitar": false,
            "partId": 5,
            "originalPartId": 5
        }
    ],
    "original_tracks": [
        {
            "instrumentId": 30,
            "instrument": "Distortion Guitar",
            "views": 3770,
            "name": "Willie Adler",
            "tuning": [
                64,
                59,
                55,
                50,
                45,
                38
            ],
            "difficulty": 4,
            "hash": "guitar_hF7BIQ5m",
            "title": "Willie Adler - Distortion Guitar",
            "isDrums": false,
            "isBassGuitar": false,
            "isGuitar": true,
            "partId": 0
        },
        {
            "instrumentId": 30,
            "instrument": "Distortion Guitar",
            "views": 288,
            "name": "Mark Morton",
            "tuning": [
                64,
                59,
                55,
                50,
                45,
                38
            ],
            "difficulty": 4,
            "hash": "guitar_sfDg1i7E",
            "title": "Mark Morton - Distortion Guitar",
            "isDrums": false,
            "isBassGuitar": false,
            "isGuitar": true,
            "partId": 1
        },
        {
            "instrumentId": 30,
            "instrument": "Distortion Guitar",
            "views": 421,
            "name": "Solo guitar 1",
            "tuning": [
                64,
                59,
                55,
                50,
                45,
                40
            ],
            "difficulty": 4,
            "hash": "guitar_g4kmgK6v",
            "title": "Solo guitar 1 - Distortion Guitar",
            "isDrums": false,
            "isBassGuitar": false,
            "isGuitar": true,
            "partId": 2
        },
        {
            "instrumentId": 30,
            "instrument": "Distortion Guitar",
            "views": 98,
            "name": "Solo guitar 2",
            "tuning": [
                64,
                59,
                55,
                50,
                45,
                38
            ],
            "difficulty": 4,
            "hash": "guitar_i0Xkk4Wm",
            "title": "Solo guitar 2 - Distortion Guitar",
            "isDrums": false,
            "isBassGuitar": false,
            "isGuitar": true,
            "partId": 3
        },
        {
            "instrumentId": 34,
            "instrument": "Electric Bass (pick)",
            "views": 313,
            "name": "John Campbell",
            "tuning": [
                43,
                38,
                33,
                26
            ],
            "hash": "bass_QVLYDfhW",
            "title": "John Campbell - Electric Bass (pick)",
            "isDrums": false,
            "isBassGuitar": true,
            "isGuitar": false,
            "partId": 4
        },
        {
            "instrumentId": 1024,
            "instrument": "Drums",
            "views": 17,
            "name": "Chris Adler",
            "hash": "drums_hES3js5s",
            "title": "Chris Adler - Drums",
            "isDrums": true,
            "isBassGuitar": false,
            "isGuitar": false,
            "partId": 5
        }
    ]
}