{
    "song_id": 11819,
    "revision_id": 371619,
    "prev_revision_id": null,
    "image": "khkbma9T5rTtRArKEi_Ao",
    "name": "Autre_Dialogue_(medley_Version)",
    "tracks": [
        {
            "instrumentId": 24,
            "instrument": "Acoustic Guitar (nylon)",
            "views": 3,
            "name": "Guitare",
            "tuning": [
                64,
                59,
                55,
                50,
                45,
                40
            ],
            "difficulty": 4,
            "hash": "guitar_8MRvJPr5",
            "title": "Guitare - Acoustic Guitar (nylon)",
            "isDrums": false,
            "isBassGuitar": false,
            "isGuitar": true,
            "partId": 0,
            "originalPartId": 0
        },
        {
            "instrumentId": 80,
            "instrument": "Lead 1 (square)",
            "views": 0,
            "name": "SynthLead1",
            "tuning": [
                64,
                59,
                55,
                50,
                45,
                40
            ],
            "hash": "other_eJRt788P",
            "title": "SynthLead1 - Lead 1 (square)",
            "isDrums": false,
            "isBassGuitar": false,
            "isGuitar": false,
            "partId": 1,
            "originalPartId": 1
        },
        {
            "instrumentId": 81,
            "instrument": "Lead 2 (sawtooth)",
            "views": 0,
            "name": "SynthLead2",
            "tuning": [
                64,
                59,
                55,
                50,
                45,
                40
            ],
            "hash": "other_zdFwHZq2",
            "title": "SynthLead2 - Lead 2 (sawtooth)",
            "isDrums": false,
            "isBassGuitar": false,
            "isGuitar": false,
            "partId": 2,
            "originalPartId": 2
        },
        {
            "instrumentId": 33,
            "instrument": "Electric Bass (finger)",
            "views": 2,
            "name": "Basse",
            "tuning": [
                52,
                47,
                43,
                38,
                33,
                28
            ],
            "hash": "bass_mfoFbdyW",
            "title": "Basse - Electric Bass (finger)",
            "isDrums": false,
            "isBassGuitar": true,
            "isGuitar": false,
            "partId": 3,
            "originalPartId": 3
        }
    ],
    "original_tracks": [
        {
            "instrumentId": 24,
            "instrument": "Acoustic Guitar (nylon)",
            "views": 3,
            "name": "Guitare",
            "tuning": [
                64,
                59,
                55,
                50,
                45,
                40
            ],
            "difficulty": 4,
            "hash": "guitar_8MRvJPr5",
            "title": "Guitare - Acoustic Guitar (nylon)",
            "isDrums": false,
            "isBassGuitar": false,
            "isGuitar": true,
            "partId": 0
        },
        {
            "instrumentId": 80,
            "instrument": "Lead 1 (square)",
            "views": 0,
            "name": "SynthLead1",
            "tuning": [
                64,
                59,
                55,
                50,
                45,
                40
            ],
            "hash": "other_eJRt788P",
            "title": "SynthLead1 - Lead 1 (square)",
            "isDrums": false,
            "isBassGuitar": false,
            "isGuitar": false,
            "partId": 1
        },
        {
            "instrumentId": 81,
            "instrument": "Lead 2 (sawtooth)",
            "views": 0,
            "name": "SynthLead2",
            "tuning": [
                64,
                59,
                55,
                50,
                45,
                40
            ],
            "hash": "other_zdFwHZq2",
            "title": "SynthLead2 - Lead 2 (sawtooth)",
            "isDrums": false,
            "isBassGuitar": false,
            "isGuitar": false,
            "partId": 2
        },
        {
            "instrumentId": 33,
            "instrument": "Electric Bass (finger)",
            "views": 2,
            "name": "Basse",
            "tuning": [
                52,
                47,
                43,
                38,
                33,
                28
            ],
            "hash": "bass_mfoFbdyW",
            "title": "Basse - Electric Bass (finger)",
            "isDrums": false,
            "isBassGuitar": true,
            "isGuitar": false,
            "partId": 3
        }
    ]
}