{
    "song_id": 4909,
    "revision_id": 1006381,
    "prev_revision_id": 7573,
    "image": "v3-5-24-qlgCbylHH8b59h1i",
    "name": "Blood_Red_Summer",
    "tracks": [
        {
            "instrumentId": 30,
            "instrument": "Distortion Guitar",
            "views": 153,
            "name": "Claudio",
            "tuning": [
                64,
                59,
                55,
                50,
                45,
                40
            ],
            "difficulty": 2,
            "hash": "guitar_yQ9gYWfl",
            "title": "Claudio - Distortion Guitar",
            "isDrums": false,
            "isBassGuitar": false,
            "isGuitar": true,
            "partId": 0,
            "originalPartId": 0
        },
        {
            "instrumentId": 27,
            "instrument": "Electric Guitar (clean)",
            "views": 237,
            "name": "Travis",
            "tuning": [
                64,
                59,
                55,
                50,
                45,
                40
            ],
            "difficulty": 2,
            "hash": "guitar_NAzx6CN2",
            "title": "Travis - Electric Guitar (clean)",
            "isDrums": false,
            "isBassGuitar": false,
            "isGuitar": true,
            "partId": 1,
            "originalPartId": 1
        },
        {
            "instrumentId": 33,
            "instrument": "Electric Bass (finger)",
            "views": 38,
            "name": "Mike",
            "tuning": [
                43,
                38,
                33,
                28
            ],
            "hash": "bass_X20whmCi",
            "title": "Mike - Electric Bass (finger)",
            "isDrums": false,
            "isBassGuitar": true,
            "isGuitar": false,
            "partId": 2,
            "originalPartId": 2
        },
        {
            "instrumentId": 1024,
            "instrument": "Drums",
            "views": 26,
            "name": "Josh",
            "hash": "drums_sT0o0Pbn",
            "title": "Josh - Drums",
            "isDrums": true,
            "isBassGuitar": false,
            "isGuitar": false,
            "partId": 3,
            "originalPartId": 3
        }
    ],
    "original_tracks": [
        {
            "instrumentId": 30,
            "instrument": "Distortion Guitar",
            "views": 153,
            "name": "Claudio",
            "tuning": [
                64,
                59,
                55,
                50,
                45,
                40
            ],
            "difficulty": 2,
            "hash": "guitar_yQ9gYWfl",
            "title": "Claudio - Distortion Guitar",
            "isDrums": false,
            "isBassGuitar": false,
            "isGuitar": true,
            "partId": 0
        },
        {
            "instrumentId": 27,
            "instrument": "Electric Guitar (clean)",
            "views": 237,
            "name": "Travis",
            "tuning": [
                64,
                59,
                55,
                50,
                45,
                40
            ],
            "difficulty": 2,
            "hash": "guitar_NAzx6CN2",
            "title": "Travis - Electric Guitar (clean)",
            "isDrums": false,
            "isBassGuitar": false,
            "isGuitar": true,
            "partId": 1
        },
        {
            "instrumentId": 33,
            "instrument": "Electric Bass (finger)",
            "views": 38,
            "name": "Mike",
            "tuning": [
                43,
                38,
                33,
                28
            ],
            "hash": "bass_X20whmCi",
            "title": "Mike - Electric Bass (finger)",
            "isDrums": false,
            "isBassGuitar": true,
            "isGuitar": false,
            "partId": 2
        },
        {
            "instrumentId": 1024,
            "instrument": "Drums",
            "views": 26,
            "name": "Josh",
            "hash": "drums_sT0o0Pbn",
            "title": "Josh - Drums",
            "isDrums": true,
            "isBassGuitar": false,
            "isGuitar": false,
            "partId": 3
        }
    ]
}