{
    "song_id": 9452,
    "revision_id": 27302,
    "prev_revision_id": null,
    "image": "gFPApJDhVbuAOZJiQn-nR",
    "name": "Down_Child",
    "tracks": [
        {
            "instrumentId": 27,
            "instrument": "Electric Guitar (clean)",
            "views": 10,
            "name": "Guitar I",
            "tuning": [
                64,
                59,
                55,
                50,
                45,
                40
            ],
            "difficulty": 3,
            "hash": "guitar_GHULy81U",
            "title": "Guitar I - Electric Guitar (clean)",
            "isDrums": false,
            "isBassGuitar": false,
            "isGuitar": true,
            "partId": 0,
            "originalPartId": 0
        },
        {
            "instrumentId": 27,
            "instrument": "Electric Guitar (clean)",
            "views": 1,
            "name": "Guitar II",
            "tuning": [
                64,
                59,
                55,
                50,
                45,
                40
            ],
            "difficulty": 2,
            "hash": "guitar_ESP4zs4D",
            "title": "Guitar II - Electric Guitar (clean)",
            "isDrums": false,
            "isBassGuitar": false,
            "isGuitar": true,
            "partId": 1,
            "originalPartId": 1
        },
        {
            "instrumentId": 24,
            "instrument": "Acoustic Guitar (nylon)",
            "views": 0,
            "name": "Guitar III",
            "tuning": [
                64,
                59,
                55,
                50,
                45,
                40
            ],
            "difficulty": 1,
            "hash": "guitar_kXl1BgzB",
            "title": "Guitar III - Acoustic Guitar (nylon)",
            "isDrums": false,
            "isBassGuitar": false,
            "isGuitar": true,
            "partId": 2,
            "originalPartId": 2
        }
    ],
    "original_tracks": [
        {
            "instrumentId": 27,
            "instrument": "Electric Guitar (clean)",
            "views": 10,
            "name": "Guitar I",
            "tuning": [
                64,
                59,
                55,
                50,
                45,
                40
            ],
            "difficulty": 3,
            "hash": "guitar_GHULy81U",
            "title": "Guitar I - Electric Guitar (clean)",
            "isDrums": false,
            "isBassGuitar": false,
            "isGuitar": true,
            "partId": 0
        },
        {
            "instrumentId": 27,
            "instrument": "Electric Guitar (clean)",
            "views": 1,
            "name": "Guitar II",
            "tuning": [
                64,
                59,
                55,
                50,
                45,
                40
            ],
            "difficulty": 2,
            "hash": "guitar_ESP4zs4D",
            "title": "Guitar II - Electric Guitar (clean)",
            "isDrums": false,
            "isBassGuitar": false,
            "isGuitar": true,
            "partId": 1
        },
        {
            "instrumentId": 24,
            "instrument": "Acoustic Guitar (nylon)",
            "views": 0,
            "name": "Guitar III",
            "tuning": [
                64,
                59,
                55,
                50,
                45,
                40
            ],
            "difficulty": 1,
            "hash": "guitar_kXl1BgzB",
            "title": "Guitar III - Acoustic Guitar (nylon)",
            "isDrums": false,
            "isBassGuitar": false,
            "isGuitar": true,
            "partId": 2
        }
    ]
}