{
    "song_id": 1109,
    "revision_id": 3304,
    "prev_revision_id": null,
    "image": "Asu0PiRZk3rK8nYY1Lm16",
    "name": "Enigma",
    "tracks": [
        {
            "instrumentId": 48,
            "instrument": "String Ensemble 1",
            "views": 0,
            "name": "Cordas",
            "tuning": [
                64,
                59,
                55,
                50,
                45,
                40
            ],
            "hash": "other_385CfqKb",
            "title": "Cordas - String Ensemble 1",
            "isDrums": false,
            "isBassGuitar": false,
            "isGuitar": false,
            "partId": 0,
            "originalPartId": 0
        },
        {
            "instrumentId": 0,
            "instrument": "Acoustic Grand Piano",
            "views": 0,
            "name": "",
            "tuning": [
                64,
                59,
                55,
                50,
                45,
                40
            ],
            "hash": "other_U62oDZXg",
            "title": "Acoustic Grand Piano",
            "isDrums": false,
            "isBassGuitar": false,
            "isGuitar": false,
            "partId": 1,
            "originalPartId": 1
        },
        {
            "instrumentId": 80,
            "instrument": "Lead 1 (square)",
            "views": 0,
            "name": "Efeito",
            "tuning": [
                64,
                59,
                55,
                50,
                45,
                40
            ],
            "hash": "other_gMqyEDoM",
            "title": "Efeito - Lead 1 (square)",
            "isDrums": false,
            "isBassGuitar": false,
            "isGuitar": false,
            "partId": 2,
            "originalPartId": 2
        },
        {
            "instrumentId": 30,
            "instrument": "Distortion Guitar",
            "views": 7,
            "name": "Guitarra",
            "tuning": [
                64,
                59,
                55,
                50,
                45,
                40
            ],
            "difficulty": 5,
            "hash": "guitar_E0KKHY2u",
            "title": "Guitarra - Distortion Guitar 1",
            "isDrums": false,
            "isBassGuitar": false,
            "isGuitar": true,
            "partId": 3,
            "originalPartId": 3
        },
        {
            "instrumentId": 30,
            "instrument": "Distortion Guitar",
            "views": 0,
            "name": "Guitarra",
            "tuning": [
                64,
                59,
                55,
                50,
                45,
                40
            ],
            "difficulty": 6,
            "hash": "guitar_H0bnWOmD",
            "title": "Guitarra - Distortion Guitar 2",
            "isDrums": false,
            "isBassGuitar": false,
            "isGuitar": true,
            "partId": 4,
            "originalPartId": 4
        },
        {
            "instrumentId": 30,
            "instrument": "Distortion Guitar",
            "views": 0,
            "name": "Guitarra",
            "tuning": [
                64,
                59,
                55,
                50,
                45,
                40
            ],
            "difficulty": 4,
            "hash": "guitar_7G95q58X",
            "title": "Guitarra - Distortion Guitar 3",
            "isDrums": false,
            "isBassGuitar": false,
            "isGuitar": true,
            "partId": 5,
            "originalPartId": 5
        },
        {
            "instrumentId": 33,
            "instrument": "Electric Bass (finger)",
            "views": 0,
            "name": "Baixo",
            "tuning": [
                43,
                38,
                33,
                28
            ],
            "hash": "bass_3zTbpjD1",
            "title": "Baixo - Electric Bass (finger)",
            "isDrums": false,
            "isBassGuitar": true,
            "isGuitar": false,
            "partId": 6,
            "originalPartId": 6
        },
        {
            "instrumentId": 1024,
            "instrument": "Drums",
            "views": 0,
            "name": "Bateria",
            "hash": "drums_vZmS3PWw",
            "title": "Bateria - Drums",
            "isDrums": true,
            "isBassGuitar": false,
            "isGuitar": false,
            "partId": 7,
            "originalPartId": 7
        },
        {
            "instrumentId": 81,
            "instrument": "Lead 2 (sawtooth)",
            "views": 0,
            "name": "Vocal",
            "tuning": [
                64,
                59,
                55,
                50,
                45,
                40
            ],
            "hash": "vocals_SUmLcsza",
            "title": "Vocal - Lead 2 (sawtooth)",
            "isDrums": false,
            "isBassGuitar": false,
            "isGuitar": false,
            "partId": 8,
            "originalPartId": 8
        },
        {
            "instrumentId": 52,
            "instrument": "Choir Aahs",
            "views": 0,
            "name": "Vocal",
            "tuning": [
                64,
                59,
                55,
                50,
                45,
                40
            ],
            "hash": "vocals_N2XzSO42",
            "title": "Vocal - Choir Aahs",
            "isDrums": false,
            "isBassGuitar": false,
            "isGuitar": false,
            "partId": 9,
            "originalPartId": 9
        }
    ],
    "original_tracks": [
        {
            "instrumentId": 48,
            "instrument": "String Ensemble 1",
            "views": 0,
            "name": "Cordas",
            "tuning": [
                64,
                59,
                55,
                50,
                45,
                40
            ],
            "hash": "other_385CfqKb",
            "title": "Cordas - String Ensemble 1",
            "isDrums": false,
            "isBassGuitar": false,
            "isGuitar": false,
            "partId": 0
        },
        {
            "instrumentId": 0,
            "instrument": "Acoustic Grand Piano",
            "views": 0,
            "name": "",
            "tuning": [
                64,
                59,
                55,
                50,
                45,
                40
            ],
            "hash": "other_U62oDZXg",
            "title": "Acoustic Grand Piano",
            "isDrums": false,
            "isBassGuitar": false,
            "isGuitar": false,
            "partId": 1
        },
        {
            "instrumentId": 80,
            "instrument": "Lead 1 (square)",
            "views": 0,
            "name": "Efeito",
            "tuning": [
                64,
                59,
                55,
                50,
                45,
                40
            ],
            "hash": "other_gMqyEDoM",
            "title": "Efeito - Lead 1 (square)",
            "isDrums": false,
            "isBassGuitar": false,
            "isGuitar": false,
            "partId": 2
        },
        {
            "instrumentId": 30,
            "instrument": "Distortion Guitar",
            "views": 7,
            "name": "Guitarra",
            "tuning": [
                64,
                59,
                55,
                50,
                45,
                40
            ],
            "difficulty": 5,
            "hash": "guitar_E0KKHY2u",
            "title": "Guitarra - Distortion Guitar 1",
            "isDrums": false,
            "isBassGuitar": false,
            "isGuitar": true,
            "partId": 3
        },
        {
            "instrumentId": 30,
            "instrument": "Distortion Guitar",
            "views": 0,
            "name": "Guitarra",
            "tuning": [
                64,
                59,
                55,
                50,
                45,
                40
            ],
            "difficulty": 6,
            "hash": "guitar_H0bnWOmD",
            "title": "Guitarra - Distortion Guitar 2",
            "isDrums": false,
            "isBassGuitar": false,
            "isGuitar": true,
            "partId": 4
        },
        {
            "instrumentId": 30,
            "instrument": "Distortion Guitar",
            "views": 0,
            "name": "Guitarra",
            "tuning": [
                64,
                59,
                55,
                50,
                45,
                40
            ],
            "difficulty": 4,
            "hash": "guitar_7G95q58X",
            "title": "Guitarra - Distortion Guitar 3",
            "isDrums": false,
            "isBassGuitar": false,
            "isGuitar": true,
            "partId": 5
        },
        {
            "instrumentId": 33,
            "instrument": "Electric Bass (finger)",
            "views": 0,
            "name": "Baixo",
            "tuning": [
                43,
                38,
                33,
                28
            ],
            "hash": "bass_3zTbpjD1",
            "title": "Baixo - Electric Bass (finger)",
            "isDrums": false,
            "isBassGuitar": true,
            "isGuitar": false,
            "partId": 6
        },
        {
            "instrumentId": 1024,
            "instrument": "Drums",
            "views": 0,
            "name": "Bateria",
            "hash": "drums_vZmS3PWw",
            "title": "Bateria - Drums",
            "isDrums": true,
            "isBassGuitar": false,
            "isGuitar": false,
            "partId": 7
        },
        {
            "instrumentId": 81,
            "instrument": "Lead 2 (sawtooth)",
            "views": 0,
            "name": "Vocal",
            "tuning": [
                64,
                59,
                55,
                50,
                45,
                40
            ],
            "hash": "vocals_SUmLcsza",
            "title": "Vocal - Lead 2 (sawtooth)",
            "isDrums": false,
            "isBassGuitar": false,
            "isGuitar": false,
            "partId": 8
        },
        {
            "instrumentId": 52,
            "instrument": "Choir Aahs",
            "views": 0,
            "name": "Vocal",
            "tuning": [
                64,
                59,
                55,
                50,
                45,
                40
            ],
            "hash": "vocals_N2XzSO42",
            "title": "Vocal - Choir Aahs",
            "isDrums": false,
            "isBassGuitar": false,
            "isGuitar": false,
            "partId": 9
        }
    ]
}