{
    "song_id": 3847,
    "revision_id": 637348,
    "prev_revision_id": 349374,
    "image": "v3-0-0-fswWb9KID5oy59x0",
    "name": "Si_Seulement_Je_Pouvais_Lui_Manquer",
    "tracks": [
        {
            "instrumentId": 0,
            "instrument": "Acoustic Grand Piano",
            "views": 243,
            "name": "Piano (main droite)",
            "tuning": [
                64,
                59,
                55,
                50,
                45,
                40
            ],
            "hash": "other_aVYpLhtm",
            "title": "Piano (main droite) - Acoustic Grand Piano",
            "isDrums": false,
            "isBassGuitar": false,
            "isGuitar": false,
            "partId": 0,
            "originalPartId": 0
        },
        {
            "instrumentId": 0,
            "instrument": "Acoustic Grand Piano",
            "views": 31,
            "name": "Piano (main gauche)",
            "tuning": [
                64,
                59,
                55,
                50,
                45,
                25
            ],
            "hash": "other_BI1PO3wY",
            "title": "Piano (main gauche) - Acoustic Grand Piano",
            "isDrums": false,
            "isBassGuitar": false,
            "isGuitar": false,
            "partId": 1,
            "originalPartId": 1
        },
        {
            "instrumentId": 33,
            "instrument": "Electric Bass (finger)",
            "views": 281,
            "name": "Basse",
            "tuning": [
                43,
                38,
                33,
                28
            ],
            "hash": "bass_S1vygS32",
            "title": "Basse - Electric Bass (finger)",
            "isDrums": false,
            "isBassGuitar": true,
            "isGuitar": false,
            "partId": 2,
            "originalPartId": 2
        },
        {
            "instrumentId": 26,
            "instrument": "Electric Guitar (jazz)",
            "views": 110,
            "name": "Gtr.clean",
            "tuning": [
                64,
                59,
                55,
                50,
                45,
                40
            ],
            "difficulty": 2,
            "hash": "guitar_jNuZkMLN",
            "title": "Gtr.clean - Electric Guitar (jazz)",
            "isDrums": false,
            "isBassGuitar": false,
            "isGuitar": true,
            "partId": 3,
            "originalPartId": 3
        },
        {
            "instrumentId": 29,
            "instrument": "Overdriven Guitar",
            "views": 64,
            "name": "Gtr.satur\u00e9e.",
            "tuning": [
                64,
                59,
                55,
                50,
                45,
                40
            ],
            "difficulty": 3,
            "hash": "guitar_B5IvN4fn",
            "title": "Gtr.satur\u00e9e. - Overdriven Guitar",
            "isDrums": false,
            "isBassGuitar": false,
            "isGuitar": true,
            "partId": 4,
            "originalPartId": 4
        },
        {
            "instrumentId": 1024,
            "instrument": "Drums",
            "views": 22,
            "name": "Batterie",
            "hash": "drums_0ZPJhDCC",
            "title": "Batterie - Drums",
            "isDrums": true,
            "isBassGuitar": false,
            "isGuitar": false,
            "partId": 5,
            "originalPartId": 5
        },
        {
            "instrumentId": 81,
            "instrument": "Lead 2 (sawtooth)",
            "views": 41,
            "name": "Overdub basse",
            "tuning": [
                43,
                38,
                33,
                28
            ],
            "hash": "other_nSukBpeB",
            "title": "Overdub basse - Lead 2 (sawtooth)",
            "isDrums": false,
            "isBassGuitar": false,
            "isGuitar": false,
            "partId": 6,
            "originalPartId": 6
        },
        {
            "instrumentId": 26,
            "instrument": "Electric Guitar (jazz)",
            "views": 22,
            "name": "Gtr.clean 2",
            "tuning": [
                64,
                59,
                55,
                50,
                45,
                40
            ],
            "difficulty": 2,
            "hash": "guitar_3YMqp2wt",
            "title": "Gtr.clean 2 - Electric Guitar (jazz)",
            "isDrums": false,
            "isBassGuitar": false,
            "isGuitar": true,
            "partId": 7,
            "originalPartId": 7
        },
        {
            "instrumentId": 82,
            "instrument": "Lead 3 (calliope)",
            "views": 38,
            "name": "Voix (Calogero)",
            "tuning": [
                64,
                59,
                55,
                50,
                45,
                40
            ],
            "hash": "other_Fg85ZT48",
            "title": "Voix (Calogero) - Lead 3 (calliope)",
            "isDrums": false,
            "isBassGuitar": false,
            "isGuitar": false,
            "partId": 8,
            "originalPartId": 8
        },
        {
            "instrumentId": 29,
            "instrument": "Overdriven Guitar",
            "views": 33,
            "name": "Gtr.satur\u00e9e 2",
            "tuning": [
                64,
                59,
                55,
                50,
                45,
                40
            ],
            "difficulty": 2,
            "hash": "guitar_rMBtT3IH",
            "title": "Gtr.satur\u00e9e 2 - Overdriven Guitar",
            "isDrums": false,
            "isBassGuitar": false,
            "isGuitar": true,
            "partId": 9,
            "originalPartId": 9
        }
    ],
    "original_tracks": [
        {
            "instrumentId": 0,
            "instrument": "Acoustic Grand Piano",
            "views": 243,
            "name": "Piano (main droite)",
            "tuning": [
                64,
                59,
                55,
                50,
                45,
                40
            ],
            "hash": "other_aVYpLhtm",
            "title": "Piano (main droite) - Acoustic Grand Piano",
            "isDrums": false,
            "isBassGuitar": false,
            "isGuitar": false,
            "partId": 0
        },
        {
            "instrumentId": 0,
            "instrument": "Acoustic Grand Piano",
            "views": 31,
            "name": "Piano (main gauche)",
            "tuning": [
                64,
                59,
                55,
                50,
                45,
                25
            ],
            "hash": "other_BI1PO3wY",
            "title": "Piano (main gauche) - Acoustic Grand Piano",
            "isDrums": false,
            "isBassGuitar": false,
            "isGuitar": false,
            "partId": 1
        },
        {
            "instrumentId": 33,
            "instrument": "Electric Bass (finger)",
            "views": 281,
            "name": "Basse",
            "tuning": [
                43,
                38,
                33,
                28
            ],
            "hash": "bass_S1vygS32",
            "title": "Basse - Electric Bass (finger)",
            "isDrums": false,
            "isBassGuitar": true,
            "isGuitar": false,
            "partId": 2
        },
        {
            "instrumentId": 26,
            "instrument": "Electric Guitar (jazz)",
            "views": 110,
            "name": "Gtr.clean",
            "tuning": [
                64,
                59,
                55,
                50,
                45,
                40
            ],
            "difficulty": 2,
            "hash": "guitar_jNuZkMLN",
            "title": "Gtr.clean - Electric Guitar (jazz)",
            "isDrums": false,
            "isBassGuitar": false,
            "isGuitar": true,
            "partId": 3
        },
        {
            "instrumentId": 29,
            "instrument": "Overdriven Guitar",
            "views": 64,
            "name": "Gtr.satur\u00e9e.",
            "tuning": [
                64,
                59,
                55,
                50,
                45,
                40
            ],
            "difficulty": 3,
            "hash": "guitar_B5IvN4fn",
            "title": "Gtr.satur\u00e9e. - Overdriven Guitar",
            "isDrums": false,
            "isBassGuitar": false,
            "isGuitar": true,
            "partId": 4
        },
        {
            "instrumentId": 1024,
            "instrument": "Drums",
            "views": 22,
            "name": "Batterie",
            "hash": "drums_0ZPJhDCC",
            "title": "Batterie - Drums",
            "isDrums": true,
            "isBassGuitar": false,
            "isGuitar": false,
            "partId": 5
        },
        {
            "instrumentId": 81,
            "instrument": "Lead 2 (sawtooth)",
            "views": 41,
            "name": "Overdub basse",
            "tuning": [
                43,
                38,
                33,
                28
            ],
            "hash": "other_nSukBpeB",
            "title": "Overdub basse - Lead 2 (sawtooth)",
            "isDrums": false,
            "isBassGuitar": false,
            "isGuitar": false,
            "partId": 6
        },
        {
            "instrumentId": 26,
            "instrument": "Electric Guitar (jazz)",
            "views": 22,
            "name": "Gtr.clean 2",
            "tuning": [
                64,
                59,
                55,
                50,
                45,
                40
            ],
            "difficulty": 2,
            "hash": "guitar_3YMqp2wt",
            "title": "Gtr.clean 2 - Electric Guitar (jazz)",
            "isDrums": false,
            "isBassGuitar": false,
            "isGuitar": true,
            "partId": 7
        },
        {
            "instrumentId": 82,
            "instrument": "Lead 3 (calliope)",
            "views": 38,
            "name": "Voix (Calogero)",
            "tuning": [
                64,
                59,
                55,
                50,
                45,
                40
            ],
            "hash": "other_Fg85ZT48",
            "title": "Voix (Calogero) - Lead 3 (calliope)",
            "isDrums": false,
            "isBassGuitar": false,
            "isGuitar": false,
            "partId": 8
        },
        {
            "instrumentId": 29,
            "instrument": "Overdriven Guitar",
            "views": 33,
            "name": "Gtr.satur\u00e9e 2",
            "tuning": [
                64,
                59,
                55,
                50,
                45,
                40
            ],
            "difficulty": 2,
            "hash": "guitar_rMBtT3IH",
            "title": "Gtr.satur\u00e9e 2 - Overdriven Guitar",
            "isDrums": false,
            "isBassGuitar": false,
            "isGuitar": true,
            "partId": 9
        }
    ]
}