{
    "song_id": 4431,
    "revision_id": 6279,
    "prev_revision_id": null,
    "image": "YgtQmXZ4LrH-bnjiFg9Ub",
    "name": "Svete_Tradicije",
    "tracks": [
        {
            "instrumentId": 34,
            "instrument": "Electric Bass (pick)",
            "views": 0,
            "name": "Steza 1",
            "tuning": [
                43,
                38,
                33,
                28
            ],
            "hash": "bass_KnSpbaE1",
            "title": "Steza 1 - Electric Bass (pick)",
            "isDrums": false,
            "isBassGuitar": true,
            "isGuitar": false,
            "partId": 0,
            "originalPartId": 0
        }
    ],
    "original_tracks": [
        {
            "instrumentId": 34,
            "instrument": "Electric Bass (pick)",
            "views": 0,
            "name": "Steza 1",
            "tuning": [
                43,
                38,
                33,
                28
            ],
            "hash": "bass_KnSpbaE1",
            "title": "Steza 1 - Electric Bass (pick)",
            "isDrums": false,
            "isBassGuitar": true,
            "isGuitar": false,
            "partId": 0
        }
    ]
}