{
    "song_id": 12577,
    "revision_id": 776795,
    "prev_revision_id": 774552,
    "image": "v3-5-0-GrudnUxzfOrz-t_d",
    "name": "Vanished",
    "tracks": [
        {
            "instrumentId": 30,
            "instrument": "Distortion Guitar",
            "views": 458,
            "name": "Guitar 1",
            "tuning": [
                63,
                58,
                54,
                49,
                44,
                39,
                34
            ],
            "difficulty": 3,
            "hash": "guitar_SowGAPqQ",
            "title": "Guitar 1 - Distortion Guitar",
            "isDrums": false,
            "isBassGuitar": false,
            "isGuitar": true,
            "partId": 0,
            "originalPartId": 0
        },
        {
            "instrumentId": 30,
            "instrument": "Distortion Guitar",
            "views": 3,
            "name": "Guitar 2",
            "tuning": [
                63,
                58,
                54,
                49,
                44,
                39,
                34
            ],
            "difficulty": 3,
            "hash": "guitar_Yp9veYQs",
            "title": "Guitar 2 - Distortion Guitar",
            "isDrums": false,
            "isBassGuitar": false,
            "isGuitar": true,
            "partId": 1,
            "originalPartId": 1
        },
        {
            "instrumentId": 33,
            "instrument": "Electric Bass (finger)",
            "views": 8,
            "name": "",
            "tuning": [
                42,
                37,
                32,
                27,
                22
            ],
            "hash": "bass_8UmOEUBf",
            "title": "Electric Bass (finger)",
            "isDrums": false,
            "isBassGuitar": true,
            "isGuitar": false,
            "partId": 2,
            "originalPartId": 2
        },
        {
            "instrumentId": 30,
            "instrument": "Distortion Guitar",
            "views": 51,
            "name": "Lead Guitar",
            "tuning": [
                63,
                58,
                54,
                49,
                44,
                39,
                34
            ],
            "difficulty": 2,
            "hash": "guitar_Jzy3Fvyc",
            "title": "Lead Guitar - Distortion Guitar",
            "isDrums": false,
            "isBassGuitar": false,
            "isGuitar": true,
            "partId": 3,
            "originalPartId": 3
        },
        {
            "instrumentId": 1024,
            "instrument": "Drums",
            "views": 75,
            "name": "",
            "hash": "drums_XmXM5lzs",
            "title": "Drums",
            "isDrums": true,
            "isBassGuitar": false,
            "isGuitar": false,
            "partId": 4,
            "originalPartId": 4
        },
        {
            "instrumentId": 27,
            "instrument": "Electric Guitar (clean)",
            "views": 96,
            "name": "Clean Guitar",
            "tuning": [
                63,
                58,
                54,
                49,
                44,
                39,
                34
            ],
            "difficulty": 2,
            "hash": "guitar_8lgIQS9d",
            "title": "Clean Guitar - Electric Guitar (clean)",
            "isDrums": false,
            "isBassGuitar": false,
            "isGuitar": true,
            "partId": 5,
            "originalPartId": 5
        }
    ],
    "original_tracks": [
        {
            "instrumentId": 30,
            "instrument": "Distortion Guitar",
            "views": 458,
            "name": "Guitar 1",
            "tuning": [
                63,
                58,
                54,
                49,
                44,
                39,
                34
            ],
            "difficulty": 3,
            "hash": "guitar_SowGAPqQ",
            "title": "Guitar 1 - Distortion Guitar",
            "isDrums": false,
            "isBassGuitar": false,
            "isGuitar": true,
            "partId": 0
        },
        {
            "instrumentId": 30,
            "instrument": "Distortion Guitar",
            "views": 3,
            "name": "Guitar 2",
            "tuning": [
                63,
                58,
                54,
                49,
                44,
                39,
                34
            ],
            "difficulty": 3,
            "hash": "guitar_Yp9veYQs",
            "title": "Guitar 2 - Distortion Guitar",
            "isDrums": false,
            "isBassGuitar": false,
            "isGuitar": true,
            "partId": 1
        },
        {
            "instrumentId": 33,
            "instrument": "Electric Bass (finger)",
            "views": 8,
            "name": "",
            "tuning": [
                42,
                37,
                32,
                27,
                22
            ],
            "hash": "bass_8UmOEUBf",
            "title": "Electric Bass (finger)",
            "isDrums": false,
            "isBassGuitar": true,
            "isGuitar": false,
            "partId": 2
        },
        {
            "instrumentId": 30,
            "instrument": "Distortion Guitar",
            "views": 51,
            "name": "Lead Guitar",
            "tuning": [
                63,
                58,
                54,
                49,
                44,
                39,
                34
            ],
            "difficulty": 2,
            "hash": "guitar_Jzy3Fvyc",
            "title": "Lead Guitar - Distortion Guitar",
            "isDrums": false,
            "isBassGuitar": false,
            "isGuitar": true,
            "partId": 3
        },
        {
            "instrumentId": 1024,
            "instrument": "Drums",
            "views": 75,
            "name": "",
            "hash": "drums_XmXM5lzs",
            "title": "Drums",
            "isDrums": true,
            "isBassGuitar": false,
            "isGuitar": false,
            "partId": 4
        },
        {
            "instrumentId": 27,
            "instrument": "Electric Guitar (clean)",
            "views": 96,
            "name": "Clean Guitar",
            "tuning": [
                63,
                58,
                54,
                49,
                44,
                39,
                34
            ],
            "difficulty": 2,
            "hash": "guitar_8lgIQS9d",
            "title": "Clean Guitar - Electric Guitar (clean)",
            "isDrums": false,
            "isBassGuitar": false,
            "isGuitar": true,
            "partId": 5
        }
    ]
}